AriaQuanta/__init__.py
AriaQuanta/_utils.py
AriaQuanta/_version.py
AriaQuanta/config.py
AriaQuanta/algorithms/__init__.py
AriaQuanta/algorithms/dj_algorithm.py
AriaQuanta/algorithms/eigen_solver.py
AriaQuanta/algorithms/grover_algorithm.py
AriaQuanta/algorithms/iqft_algorithm.py
AriaQuanta/algorithms/qaoa_algorithm.py
AriaQuanta/algorithms/qft_algorithm.py
AriaQuanta/algorithms/qpe_algorithm.py
AriaQuanta/algorithms/vqe_algorithm.py
AriaQuanta/aqc/__init__.py
AriaQuanta/aqc/ansatz.py
AriaQuanta/aqc/circuit.py
AriaQuanta/aqc/measure.py
AriaQuanta/aqc/noise.py
AriaQuanta/aqc/operations.py
AriaQuanta/aqc/qubit.py
AriaQuanta/aqc/visualization.py
AriaQuanta/aqc/gatelibrary/__init__.py
AriaQuanta/aqc/gatelibrary/arxived_gatetriple.py
AriaQuanta/aqc/gatelibrary/gatecontrol.py
AriaQuanta/aqc/gatelibrary/gatecontroln.py
AriaQuanta/aqc/gatelibrary/gatecustom.py
AriaQuanta/aqc/gatelibrary/gatedouble.py
AriaQuanta/aqc/gatelibrary/gatesingle.py
AriaQuanta/backend/__init__.py
AriaQuanta/backend/job.py
AriaQuanta/backend/result.py
AriaQuanta/backend/simulator.py
ariaquanta-0.1.7.dist-info/licenses/LICENSE
ariaquanta-0.1.7.dist-info/METADATA
ariaquanta-0.1.7.dist-info/WHEEL
ariaquanta-0.1.7.dist-info/top_level.txt
ariaquanta-0.1.7.dist-info/RECORD
